cuoco/__init__.py
cuoco/dataCleaning.py
cuoco/dataModeling.py
cuoco/dataPipeline.py
cuoco/dataPresentation.py
cuoco/jsonReading.py
cuoco/mainTest.py
cuoco-1.0.0.dist-info/LICENSE
cuoco-1.0.0.dist-info/METADATA
cuoco-1.0.0.dist-info/WHEEL
cuoco-1.0.0.dist-info/top_level.txt
cuoco-1.0.0.dist-info/RECORD
