Metadata-Version: 2.1
Name: cuoco
Version: 1.0.0
Summary: Cuoco is a tool for automatic data preprocessing. Cuoco comes from Italy, means chef.
Author: Francisco de Borja Garcia Lamas
Author-email: borjagl2014@gmail.com
License: : OSI Approved :: MIT License
Requires-Python: >=3.6
License-File: LICENSE
Requires-Dist: numpy
Requires-Dist: pandas
Requires-Dist: imblearn
